.gitignore
CHANGES.txt
COPYRIGHT.txt
INSTALL.txt
README.txt
bootstrap.py
buildout.cfg
setup.py
src/sterch/__init__.py
src/sterch.conveyor.egg-info/PKG-INFO
src/sterch.conveyor.egg-info/SOURCES.txt
src/sterch.conveyor.egg-info/dependency_links.txt
src/sterch.conveyor.egg-info/namespace_packages.txt
src/sterch.conveyor.egg-info/requires.txt
src/sterch.conveyor.egg-info/top_level.txt
src/sterch/conveyor/README.txt
src/sterch/conveyor/__init__.py
src/sterch/conveyor/assistance.py
src/sterch/conveyor/configure.zcml
src/sterch/conveyor/conveyor.py
src/sterch/conveyor/group.py
src/sterch/conveyor/interfaces.py
src/sterch/conveyor/meta.zcml
src/sterch/conveyor/metaconfigure.py
src/sterch/conveyor/metadirectives.py
src/sterch/conveyor/stage.py
src/sterch/conveyor/worker.py
src/sterch/conveyor/tests/__init__.py
src/sterch/conveyor/tests/activities.py
src/sterch/conveyor/tests/setup.py
src/sterch/conveyor/tests/test_flow.py
src/sterch/conveyor/tests/test_zcml.py
src/sterch/conveyor/tests/zcml/__init__.py
src/sterch/conveyor/tests/zcml/dummy_stages.zcml
src/sterch/conveyor/tests/zcml/event.zcml
src/sterch/conveyor/tests/zcml/final_stage_unreachable.zcml
src/sterch/conveyor/tests/zcml/loop.zcml
src/sterch/conveyor/tests/zcml/no_final_stage.zcml
src/sterch/conveyor/tests/zcml/no_init_stage.zcml
src/sterch/conveyor/tests/zcml/queue.zcml
src/sterch/conveyor/tests/zcml/simple_loop.zcml
src/sterch/conveyor/tests/zcml/valid_2stages_no_events.zcml
src/sterch/conveyor/tests/zcml/valid_2stages_with_events.zcml
src/sterch/conveyor/tests/zcml/valid_no_events.zcml
src/sterch/conveyor/tests/zcml/valid_with_events.zcml