Metadata-Version: 1.0
Name: sterch.conveyor
Version: 0.2
Summary: Provides ZCML-based tools to define simultaneous tasks processing conveyors
Home-page: http://pypi.sterch.net/sterch.conveyor
Author: Maksym Polscha
Author-email: maxp@sterch.net
License: ZPL 2.1
Platform: UNKNOWN
Classifier: Development Status :: 5 - Production/Stable
Classifier: Intended Audience :: Developers
Classifier: License :: OSI Approved :: Zope Public License
Classifier: Operating System :: OS Independent
Classifier: Programming Language :: Python :: 2.5
Classifier: Programming Language :: Python :: 2.6
Classifier: Topic :: Software Development :: Libraries :: Python Modules
